oj_signing_middleware/__init__.py
oj_signing_middleware/cookie.py
oj_signing_middleware/types.py
oj_signing_middleware-0.2.1.dist-info/LICENSE
oj_signing_middleware-0.2.1.dist-info/WHEEL
oj_signing_middleware-0.2.1.dist-info/METADATA
oj_signing_middleware-0.2.1.dist-info/RECORD
